{
  "project_info": {
    "project_number": "1093457445685",
    "project_id": "sign-38ab7",
    "storage_bucket": "sign-38ab7.appspot.com"
  },
  "client": [
    {
      "client_info": {
        "mobilesdk_app_id": "1:1093457445685:android:525ba9bdbf3247cc20c27c",
        "android_client_info": {
          "package_name": "com.example.sign"
        }
      },
      "oauth_client": [],
      "api_key": [
        {
          "current_key": "AIzaSyCeqjJ7EMMVj74guOTM3_yfkWMcj9WEVlE"
        }
      ],
      "services": {
        "appinvite_service": {
          "other_platform_oauth_client": []
        }
      }
    }
  ],
  "configuration_version": "1"
}